havsfunc.py
havsfunc-33.dist-info/METADATA
havsfunc-33.dist-info/WHEEL
havsfunc-33.dist-info/top_level.txt
havsfunc-33.dist-info/RECORD
