Metadata-Version: 2.1
Name: havsfunc
Version: 33
Summary: Holy's ported AviSynth functions for VapourSynth
Home-page: https://github.com/HomeOfVapourSynthEvolution/havsfunc
Author: HolyWu
License: UNKNOWN
Platform: UNKNOWN
Classifier: License :: OSI Approved :: The Unlicense (Unlicense)
Classifier: Operating System :: OS Independent
Classifier: Programming Language :: Python :: 3
Classifier: Programming Language :: Python :: 3 :: Only
Classifier: Topic :: Multimedia :: Video
Requires-Python: >=3.6
Requires-Dist: VapourSynth (>=57)
Requires-Dist: vsutil
